data_processing_flows/__init__.py
data_processing_flows/flow.py
data_processing_flows/flow_loader.py
data_processing_flows/flow_schema.json
data_processing_flows/substring _test.py
data_prep_toolkit_flows-0.2.0.dist-info/METADATA
data_prep_toolkit_flows-0.2.0.dist-info/WHEEL
data_prep_toolkit_flows-0.2.0.dist-info/top_level.txt
data_prep_toolkit_flows-0.2.0.dist-info/RECORD
