Metadata-Version: 2.1
Name: data_prep_toolkit-flows
Version: 0.2.0
Summary: Data Preparation Toolkit Library for creation and execution of ttansformers flows
Author-email: Alexey Roytman <aroytman@il.ibm.com>, Mohammad Nassar <Mohammad.Nassar@ibm.com>, Revital Eres <eres@il.ibm.com>
License: Apache-2.0
Keywords: data,data preprocessing,data preparation,llm,generative,ai,fine-tuning,llmapps
Requires-Python: >=3.10
Requires-Dist: data-prep-toolkit-ray ==0.2.0
Requires-Dist: kfp ==2.7.0
Requires-Dist: docker
Provides-Extra: dev
Requires-Dist: twine ; extra == 'dev'
Requires-Dist: pytest >=7.3.2 ; extra == 'dev'
Requires-Dist: pytest-dotenv >=0.5.2 ; extra == 'dev'
Requires-Dist: pytest-env >=1.0.0 ; extra == 'dev'
Requires-Dist: pre-commit >=3.3.2 ; extra == 'dev'
Requires-Dist: pytest-cov >=4.1.0 ; extra == 'dev'
Requires-Dist: pytest-mock >=3.10.0 ; extra == 'dev'
Requires-Dist: moto ==5.0.5 ; extra == 'dev'
Requires-Dist: markupsafe ==2.0.1 ; extra == 'dev'
